{
  "quizzes": [
    {
      "topic": "Flutter",
      "questions": [
        {
          "question": "What language is primarily used to write Flutter apps?",
          "options": [
            "Java",
            "Dart",
            "Kotlin",
            "Swift"
          ],
          "answer_index": 1
        },
        {
          "question": "Which widget is used for unidirectional scrolling in Flutter?",
          "options": [
            "ListView",
            "Column",
            "Stack",
            "Container"
          ],
          "answer_index": 0
        },
        {
          "question": "Which of the following is a Stateful widget in Flutter?",
          "options": [
            "Text",
            "Icon",
            "Scaffold",
            "Checkbox"
          ],
          "answer_index": 3
        },
        {
          "question": "What does the 'setState()' function do?",
          "options": [
            "Destroys the widget",
            "Renders UI frame",
            "Updates the UI state",
            "Builds routes"
          ],
          "answer_index": 2
        },
        {
          "question": "Which command is used to create a new Flutter project?",
          "options": [
            "flutter new app",
            "flutter create",
            "flutter init",
            "flutter start"
          ],
          "answer_index": 1
        },
        {
          "question": "Which widget is used to position elements relative to each other?",
          "options": [
            "Row",
            "Column",
            "Stack",
            "ListTile"
          ],
          "answer_index": 2
        },
        {
          "question": "What is the root widget of a Flutter app?",
          "options": [
            "MaterialApp",
            "Scaffold",
            "Container",
            "AppBar"
          ],
          "answer_index": 0
        },
        {
          "question": "Hot reload in Flutter preserves the state of the app?",
          "options": [
            "Always",
            "Never",
            "Only for Stateful Widgets",
            "Yes, but not always perfectly"
          ],
          "answer_index": 3
        },
        {
          "question": "Which package is used for state management in Flutter?",
          "options": [
            "Provider",
            "Express",
            "Redux Toolkit",
            "Lodash"
          ],
          "answer_index": 0
        },
        {
          "question": "Which widget helps in responsive design?",
          "options": [
            "MediaQuery",
            "SizedBox",
            "Padding",
            "Card"
          ],
          "answer_index": 0
        }
      ]
    },
    {
      "topic": "React",
      "questions": [
        {
          "question": "React is mainly used for building ____?",
          "options": [
            "Databases",
            "User Interfaces",
            "Servers",
            "Mobile Networks"
          ],
          "answer_index": 1
        },
        {
          "question": "What is JSX?",
          "options": [
            "A Java extension",
            "JavaScript XML",
            "A CSS preprocessor",
            "A database query language"
          ],
          "answer_index": 1
        },
        {
          "question": "Which hook is used to handle state in functional components?",
          "options": [
            "useState",
            "useRef",
            "useEffect",
            "useMemo"
          ],
          "answer_index": 0
        },
        {
          "question": "What is the virtual DOM?",
          "options": [
            "A copy of the real DOM",
            "A browser extension",
            "A CSS model",
            "React server"
          ],
          "answer_index": 0
        },
        {
          "question": "Which command creates a new React App?",
          "options": [
            "npm react new",
            "npx create-react-app",
            "npm start-react",
            "node create react"
          ],
          "answer_index": 1
        },
        {
          "question": "What does useEffect primarily handle?",
          "options": [
            "Routing",
            "Side Effects",
            "State",
            "Components"
          ],
          "answer_index": 1
        },
        {
          "question": "Props in React are ____?",
          "options": [
            "Mutable",
            "Read-only",
            "Optional",
            "Used only in class components"
          ],
          "answer_index": 1
        },
        {
          "question": "Which library is commonly used for routing in React?",
          "options": [
            "React Route",
            "React-Router-Dom",
            "React-DOM",
            "Next-Router"
          ],
          "answer_index": 1
        },
        {
          "question": "Which hook is used to store a value that persists without causing re-renders?",
          "options": [
            "useMemo",
            "useRef",
            "useEffect",
            "useState"
          ],
          "answer_index": 1
        },
        {
          "question": "React follows which architecture?",
          "options": [
            "MVC",
            "Two-way data binding",
            "Component-based architecture",
            "MVVM"
          ],
          "answer_index": 2
        }
      ]
    },
    {
      "topic": "UI/UX",
      "questions": [
        {
          "question": "What does UX stand for?",
          "options": [
            "User Xperience",
            "User Experience",
            "User Execution",
            "Ultimate Experience"
          ],
          "answer_index": 1
        },
        {
          "question": "Which of the following is a UI design tool?",
          "options": [
            "Figma",
            "GitHub",
            "MongoDB",
            "Postman"
          ],
          "answer_index": 0
        },
        {
          "question": "Which principle focuses on keeping the interface clean and straightforward?",
          "options": [
            "Simplicity",
            "Aesthetics",
            "Branding",
            "Storytelling"
          ],
          "answer_index": 0
        },
        {
          "question": "Which is a key UX deliverable?",
          "options": [
            "Wireframe",
            "Compiler",
            "Database schema",
            "Unit test"
          ],
          "answer_index": 0
        },
        {
          "question": "What does UI stand for?",
          "options": [
            "User Interaction",
            "User Interface",
            "Universal Input",
            "Unified Internet"
          ],
          "answer_index": 1
        },
        {
          "question": "Which of the following is a UX research method?",
          "options": [
            "User Interviews",
            "Color theory",
            "Icon design",
            "Responsive layout"
          ],
          "answer_index": 0
        },
        {
          "question": "A good UI should ensure:",
          "options": [
            "Confusion",
            "Accessibility",
            "Complexity",
            "Slow navigation"
          ],
          "answer_index": 1
        },
        {
          "question": "What is a wireframe?",
          "options": [
            "A UI style guide",
            "A low-fidelity layout blueprint",
            "Final polished UI",
            "A coding framework"
          ],
          "answer_index": 1
        },
        {
          "question": "Which color contrast ratio is recommended for accessibility?",
          "options": [
            "1:1",
            "2:1",
            "4.5:1",
            "20:1"
          ],
          "answer_index": 2
        },
        {
          "question": "Which principle relates to reducing the user\u2019s cognitive load?",
          "options": [
            "Clarity",
            "Animation",
            "Dark mode",
            "Parallax"
          ],
          "answer_index": 0
        }
      ]
    },
    {
      "topic": "C++",
      "questions": [
        {
          "question": "C++ was developed by?",
          "options": [
            "Dennis Ritchie",
            "James Gosling",
            "Bjarne Stroustrup",
            "Guido van Rossum"
          ],
          "answer_index": 2
        },
        {
          "question": "Which concept allows multiple functions with the same name?",
          "options": [
            "Encapsulation",
            "Abstraction",
            "Polymorphism",
            "Inheritance"
          ],
          "answer_index": 2
        },
        {
          "question": "Which symbol is used for single-line comments in C++?",
          "options": [
            "<!-- -->",
            "//",
            "/* */",
            "#"
          ],
          "answer_index": 1
        },
        {
          "question": "Which keyword creates an object dynamically?",
          "options": [
            "malloc",
            "alloc",
            "new",
            "create"
          ],
          "answer_index": 2
        },
        {
          "question": "Which OOP concept exposes only necessary data?",
          "options": [
            "Polymorphism",
            "Abstraction",
            "Encapsulation",
            "Multiple Inheritance"
          ],
          "answer_index": 2
        },
        {
          "question": "Which of these is used to access members of a class?",
          "options": [
            ".",
            "->",
            "::",
            "&"
          ],
          "answer_index": 0
        },
        {
          "question": "Which method is called when an object goes out of scope?",
          "options": [
            "Destructor",
            "Constructor",
            "Operator overload",
            "Friend function"
          ],
          "answer_index": 0
        },
        {
          "question": "What is the default access specifier for a class?",
          "options": [
            "public",
            "private",
            "protected",
            "internal"
          ],
          "answer_index": 1
        },
        {
          "question": "Which of the following is not a C++ data type?",
          "options": [
            "int",
            "float",
            "bool",
            "real"
          ],
          "answer_index": 3
        },
        {
          "question": "Which container is part of the Standard Template Library (STL)?",
          "options": [
            "vector",
            "arraylist",
            "listview",
            "dictionary"
          ],
          "answer_index": 0
        }
      ]
    }
  ]
}